<Properties StartupConfiguration="{DFECD860-6E12-4FEE-A2CD-62230654A53D}|Default">
  <MonoDevelop.Ide.Workbench ActiveDocument="Rpgtext1/Personnages/Enemy.cs">
    <Files>
      <File FileName="Rpgtext1/Program.cs" Line="9" Column="36" />
      <File FileName="Rpgtext1/Menu.cs" Line="102" Column="54" />
      <File FileName="Rpgtext1/Personnages/Player.cs" Line="9" Column="32" />
      <File FileName="Rpgtext1/Personnages/Personnage.cs" Line="10" Column="9" />
      <File FileName="Rpgtext1/Map.cs" Line="6" Column="38" />
      <File FileName="Rpgtext1/Personnages/Enemy.cs" Line="5" Column="6" />
    </Files>
  </MonoDevelop.Ide.Workbench>
  <MonoDevelop.Ide.ItemProperties.Rpgtext1 PreferredExecutionTarget="MonoDevelop.Default" />
  <MonoDevelop.Ide.DebuggingService.PinnedWatches />
  <MonoDevelop.Ide.Workspace ActiveConfiguration="Debug" />
  <MonoDevelop.Ide.DebuggingService.Breakpoints>
    <BreakpointStore />
  </MonoDevelop.Ide.DebuggingService.Breakpoints>
  <MultiItemStartupConfigurations />
</Properties>